dictum_backend_postgres/__init__.py
dictum_backend_postgres/postgres.py
dictum_backend_postgres-0.1.6.dist-info/entry_points.txt
dictum_backend_postgres-0.1.6.dist-info/LICENSE
dictum_backend_postgres-0.1.6.dist-info/WHEEL
dictum_backend_postgres-0.1.6.dist-info/METADATA
dictum_backend_postgres-0.1.6.dist-info/RECORD
