Metadata-Version: 2.1
Name: dictum-backend-postgres
Version: 0.1.6
Summary: Postgres backend for Dictum
Author: Mikhail Akimov
Requires-Python: >=3.8,<4
Classifier: Programming Language :: Python :: 3
Classifier: Programming Language :: Python :: 3.8
Classifier: Programming Language :: Python :: 3.9
Classifier: Programming Language :: Python :: 3.10
Classifier: Programming Language :: Python :: 3.11
Requires-Dist: dictum-core (>=0.1,<0.2)
Requires-Dist: psycopg2-binary (>=2.9.3,<3.0.0)
